flake8_numbers/__init__.py
flake8_numbers/check_numbers.py
flake8_numbers/py.typed
flake8_numbers-0.1.0.dist-info/LICENSE
flake8_numbers-0.1.0.dist-info/METADATA
flake8_numbers-0.1.0.dist-info/WHEEL
flake8_numbers-0.1.0.dist-info/entry_points.txt
flake8_numbers-0.1.0.dist-info/top_level.txt
flake8_numbers-0.1.0.dist-info/RECORD
