Metadata-Version: 2.1
Name: flake8-numbers
Version: 0.1.0
Summary: Flake8 Numbers Plugin
Author-email: Frequenz Energy-as-a-Service GmbH <floss@frequenz.com>
License: MIT
Project-URL: Changelog, https://github.com/frequenz-floss/flake8-numbers/releases
Project-URL: Issues, https://github.com/frequenz-floss/flake8-numbers/issues
Project-URL: Repository, https://github.com/frequenz-floss/flake8-numbers
Project-URL: Support, https://github.com/frequenz-floss/flake8-numbers/discussions/categories/support
Keywords: frequenz,python,lib,library,flake8_numbers,flake8,numbers,plugin
Classifier: Development Status :: 3 - Alpha
Classifier: Intended Audience :: Developers
Classifier: License :: OSI Approved :: MIT License
Classifier: Programming Language :: Python :: 3
Classifier: Programming Language :: Python :: 3 :: Only
Classifier: Topic :: Software Development :: Libraries
Classifier: Typing :: Typed
Requires-Python: <4,>=3.11
License-File: LICENSE
Requires-Dist: typing-extensions <5,>=4.5.0
Provides-Extra: dev
Requires-Dist: flake8-numbers[dev-flake8,dev-formatting,dev-mkdocs,dev-mypy,dev-noxfile,dev-pylint,dev-pytest] ; extra == 'dev'
Provides-Extra: dev-flake8
Requires-Dist: flake8 ==6.1.0 ; extra == 'dev-flake8'
Requires-Dist: flake8-docstrings ==1.7.0 ; extra == 'dev-flake8'
Requires-Dist: flake8-pyproject ==1.2.3 ; extra == 'dev-flake8'
Requires-Dist: pydoclint ==0.3.8 ; extra == 'dev-flake8'
Requires-Dist: pydocstyle ==6.3.0 ; extra == 'dev-flake8'
Provides-Extra: dev-formatting
Requires-Dist: black ==23.11.0 ; extra == 'dev-formatting'
Requires-Dist: isort ==5.12.0 ; extra == 'dev-formatting'
Provides-Extra: dev-mkdocs
Requires-Dist: mike ==1.1.2 ; extra == 'dev-mkdocs'
Requires-Dist: mkdocs-gen-files ==0.5.0 ; extra == 'dev-mkdocs'
Requires-Dist: mkdocs-literate-nav ==0.6.1 ; extra == 'dev-mkdocs'
Requires-Dist: mkdocs-material ==9.4.14 ; extra == 'dev-mkdocs'
Requires-Dist: mkdocstrings[python] ==0.24.0 ; extra == 'dev-mkdocs'
Requires-Dist: frequenz-repo-config[lib] ==0.7.5 ; extra == 'dev-mkdocs'
Provides-Extra: dev-mypy
Requires-Dist: mypy ==1.7.1 ; extra == 'dev-mypy'
Requires-Dist: flake8-numbers[dev-mkdocs,dev-noxfile,dev-pytest] ; extra == 'dev-mypy'
Provides-Extra: dev-noxfile
Requires-Dist: nox ==2023.4.22 ; extra == 'dev-noxfile'
Requires-Dist: frequenz-repo-config[lib] ==0.7.5 ; extra == 'dev-noxfile'
Provides-Extra: dev-pylint
Requires-Dist: pylint ==3.0.2 ; extra == 'dev-pylint'
Requires-Dist: flake8-numbers[dev-mkdocs,dev-noxfile,dev-pytest] ; extra == 'dev-pylint'
Provides-Extra: dev-pytest
Requires-Dist: pytest ==7.4.3 ; extra == 'dev-pytest'
Requires-Dist: frequenz-repo-config[extra-lint-examples] ==0.7.5 ; extra == 'dev-pytest'
Requires-Dist: pytest-mock ==3.12.0 ; extra == 'dev-pytest'
Requires-Dist: pytest-asyncio ==0.23.1 ; extra == 'dev-pytest'
Requires-Dist: async-solipsism ==0.5 ; extra == 'dev-pytest'
